Workbook

Sheet Dashboard
B2: FIRE RETIREMENT PLANNER
B3: Financial Independence · Retire Early · Live Free
B5: NET WORTH | D5: FIRE NUMBER | F5: FI PROGRESS | H5: YEARS TO FIRE | J5: MONTHLY SAVINGS
B6: ='Net Worth'!C42 | D6: ='Investment Growth'!C14 | F6: =IFERROR('Net Worth'!C42/'Investment Growth'!C14,0) | H6: ='Investment Growth'!C15 | J6: ='Budget & Savings'!C55
B8: FIRE MILESTONE TRACKER
B9: Milestone | D9: Target | F9: Current NW | H9: Progress | J9: Status
B10: $25K Starter | D10: 25000 | F10: ='Net Worth'!C42 | H10: =MIN(F10/D10,1) | J10: =IF(H10>=1,"✅ ACHIEVED",IF(H10>=0.5,"🔥 Halfway","⏳ Building"))
B11: $100K Club | D11: 100000 | F11: ='Net Worth'!C42 | H11: =MIN(F11/D11,1) | J11: =IF(H11>=1,"✅ ACHIEVED",IF(H11>=0.5,"🔥 Halfway","⏳ Building"))
B12: 25% FI | D12: ='Investment Growth'!C14*0.25 | F12: ='Net Worth'!C42 | H12: =MIN(F12/D12,1) | J12: =IF(H12>=1,"✅ ACHIEVED",IF(H12>=0.5,"🔥 Halfway","⏳ Building"))
B13: 50% FI | D13: ='Investment Growth'!C14*0.5 | F13: ='Net Worth'!C42 | H13: =MIN(F13/D13,1) | J13: =IF(H13>=1,"✅ ACHIEVED",IF(H13>=0.5,"🔥 Halfway","⏳ Building"))
B14: FIRE — 100% | D14: ='Investment Growth'!C14 | F14: ='Net Worth'!C42 | H14: =MIN(F14/D14,1) | J14: =IF(H14>=1,"✅ ACHIEVED",IF(H14>=0.5,"🔥 Halfway","⏳ Building"))
B16: KEY ASSUMPTIONS (edit values in their own sheets)
B17: Current Age | E17: ='Investment Growth'!C6 | G17: Annual Return (nominal) | J17: ='Investment Growth'!C7
B18: Inflation Rate | E18: ='Investment Growth'!C8 | G18: Retirement Age | J18: ='Investment Growth'!C12
B19: Safe Withdrawal Rate | E19: ='SWR Calculator'!C10 | G19: Real Return Rate | J19: ='Investment Growth'!C9

Sheet Net Worth
B2: NET WORTH TRACKER
B3: Last updated: June 24, 2026 · Update monthly for accurate FIRE tracking
B5: ASSETS
B6: Asset Category | C6: Current Value ($) | D6: % of Assets | E6: Est. Annual Return | F6: Notes
B7: Cash & Savings Account | C7: 15000 | D7: =IF(C21>0,C7/C21,0) | E7: 0.005
B8: Emergency Fund | C8: 10000 | D8: =IF(C21>0,C8/C21,0) | E8: 0.047
B9: Checking Account | C9: 5000 | D9: =IF(C21>0,C9/C21,0) | E9: 0.001
B10: 401(k) / 403(b) | C10: 85000 | D10: =IF(C21>0,C10/C21,0) | E10: 0.08
B11: Roth IRA | C11: 35000 | D11: =IF(C21>0,C11/C21,0) | E11: 0.08
B12: Traditional IRA | C12: 0 | D12: =IF(C21>0,C12/C21,0) | E12: 0.08
B13: Taxable Brokerage Account | C13: 25000 | D13: =IF(C21>0,C13/C21,0) | E13: 0.08
B14: HSA (Health Savings Account) | C14: 8000 | D14: =IF(C21>0,C14/C21,0) | E14: 0.07
B15: Real Estate — Primary Residence | C15: 350000 | D15: =IF(C21>0,C15/C21,0) | E15: 0.04
B16: Real Estate — Investment Property | C16: 0 | D16: =IF(C21>0,C16/C21,0) | E16: 0.06
B17: Vehicles | C17: 15000 | D17: =IF(C21>0,C17/C21,0) | E17: -0.1
B18: Business Equity | C18: 0 | D18: =IF(C21>0,C18/C21,0) | E18: 0.1
B19: Crypto / Alternative Assets | C19: 5000 | D19: =IF(C21>0,C19/C21,0) | E19: 0.15
B20: Other Assets | C20: 2000 | D20: =IF(C21>0,C20/C21,0) | E20: 0.02
B21: TOTAL ASSETS | C21: =SUM(C7:C20) | D21: 100.0% | E21: =SUMPRODUCT(C7:C20,E7:E20)/C21
B23: LIABILITIES
B24: Liability Category | C24: Balance Owed ($) | D24: % of Liabilities | E24: Interest Rate | F24: Notes
B25: Mortgage — Primary Residence | C25: 250000 | D25: =IF(C37>0,C25/C37,0) | E25: 0.065
B26: Mortgage — Investment Property | C26: 0 | D26: =IF(C37>0,C26/C37,0) | E26: 0.07
B27: Home Equity Loan / HELOC | C27: 0 | D27: =IF(C37>0,C27/C37,0) | E27: 0.085
B28: Auto Loan 1 | C28: 12000 | D28: =IF(C37>0,C28/C37,0) | E28: 0.059
B29: Auto Loan 2 | C29: 0 | D29: =IF(C37>0,C29/C37,0) | E29: 0
B30: Student Loans | C30: 18000 | D30: =IF(C37>0,C30/C37,0) | E30: 0.055
B31: Credit Card 1 | C31: 3500 | D31: =IF(C37>0,C31/C37,0) | E31: 0.22
B32: Credit Card 2 | C32: 0 | D32: =IF(C37>0,C32/C37,0) | E32: 0.22
B33: Personal Loan | C33: 0 | D33: =IF(C37>0,C33/C37,0) | E33: 0.12
B34: Medical Debt | C34: 0 | D34: =IF(C37>0,C34/C37,0) | E34: 0
B35: Business Debt | C35: 0 | D35: =IF(C37>0,C35/C37,0) | E35: 0.08
B36: Other Liabilities | C36: 0 | D36: =IF(C37>0,C36/C37,0) | E36: 0
B37: TOTAL LIABILITIES | C37: =SUM(C25:C36) | D37: 100.0% | E37: =IFERROR(SUMPRODUCT(C25:C36,E25:E36)/C37,0)
B39: NET WORTH SUMMARY
B40: Total Assets | C40: =C21
B41: Total Liabilities | C41: =C37
B42: NET WORTH | C42: =C21-C37
B43: Debt-to-Asset Ratio | C43: =IF(C21>0,C37/C21,0)
B44: Liquid Net Worth | C44: =SUM(C7:C14)-C37

Sheet Budget & Savings
B2: MONTHLY BUDGET & SAVINGS RATE
B3: Savings Rate is the single most important variable for achieving FIRE
B5: Category | C5: Budget/Month ($) | D5: Actual/Month ($) | E5: Variance ($) | F5: % of Income | G5: Annual Total ($)
B6: INCOME
B7: Primary Job — Net Take-Home Pay | C7: 6500 | D7: 6500 | E7: =D7-C7 | F7: =IF(C13>0,C7/C13,0) | G7: =C7*12
B8: Spouse / Partner Income | C8: 4000 | D8: 4000 | E8: =D8-C8 | F8: =IF(C13>0,C8/C13,0) | G8: =C8*12
B9: Side Hustle / Freelance | C9: 500 | D9: 500 | E9: =D9-C9 | F9: =IF(C13>0,C9/C13,0) | G9: =C9*12
B10: Rental Income | C10: 0 | D10: 0 | E10: =D10-C10 | F10: =IF(C13>0,C10/C13,0) | G10: =C10*12
B11: Dividends, Interest & Capital Gains | C11: 200 | D11: 200 | E11: =D11-C11 | F11: =IF(C13>0,C11/C13,0) | G11: =C11*12
B12: Other Income | C12: 0 | D12: 0 | E12: =D12-C12 | F12: =IF(C13>0,C12/C13,0) | G12: =C12*12
B13: TOTAL MONTHLY INCOME | C13: =SUM(C7:C12) | D13: =SUM(D7:D12) | E13: =D13-C13 | F13: 100.0% | G13: =C13*12
B15: FIXED EXPENSES
B16: Rent / Mortgage Payment | C16: 2200 | D16: 2200 | E16: =D16-C16 | F16: =IF(C13>0,C16/C13,0) | G16: =C16*12
B17: HOA Fees | C17: 0 | D17: 0 | E17: =D17-C17 | F17: =IF(C13>0,C17/C13,0) | G17: =C17*12
B18: Homeowner's / Renter's Insurance | C18: 100 | D18: 100 | E18: =D18-C18 | F18: =IF(C13>0,C18/C13,0) | G18: =C18*12
B19: Car Payment 1 | C19: 350 | D19: 350 | E19: =D19-C19 | F19: =IF(C13>0,C19/C13,0) | G19: =C19*12
B20: Car Payment 2 | C20: 0 | D20: 0 | E20: =D20-C20 | F20: =IF(C13>0,C20/C13,0) | G20: =C20*12
B21: Auto Insurance | C21: 150 | D21: 150 | E21: =D21-C21 | F21: =IF(C13>0,C21/C13,0) | G21: =C21*12
B22: Health Insurance Premium | C22: 400 | D22: 400 | E22: =D22-C22 | F22: =IF(C13>0,C22/C13,0) | G22: =C22*12
B23: Life / Disability Insurance | C23: 50 | D23: 50 | E23: =D23-C23 | F23: =IF(C13>0,C23/C13,0) | G23: =C23*12
B24: Internet | C24: 80 | D24: 80 | E24: =D24-C24 | F24: =IF(C13>0,C24/C13,0) | G24: =C24*12
B25: Phone | C25: 85 | D25: 85 | E25: =D25-C25 | F25: =IF(C13>0,C25/C13,0) | G25: =C25*12
B26: Streaming Subscriptions | C26: 50 | D26: 50 | E26: =D26-C26 | F26: =IF(C13>0,C26/C13,0) | G26: =C26*12
B27: Gym / Fitness Membership | C27: 40 | D27: 40 | E27: =D27-C27 | F27: =IF(C13>0,C27/C13,0) | G27: =C27*12
B28: TOTAL FIXED EXPENSES | C28: =SUM(C16:C27) | D28: =SUM(D16:D27) | E28: =D28-C28 | F28: =IF(C13>0,C28/C13,0) | G28: =C28*12
B30: VARIABLE EXPENSES
B31: Groceries & Household Supplies | C31: 600 | D31: 600 | E31: =D31-C31 | F31: =IF(C13>0,C31/C13,0) | G31: =C31*12
B32: Dining Out & Takeout | C32: 200 | D32: 200 | E32: =D32-C32 | F32: =IF(C13>0,C32/C13,0) | G32: =C32*12
B33: Gas & Transportation | C33: 150 | D33: 150 | E33: =D33-C33 | F33: =IF(C13>0,C33/C13,0) | G33: =C33*12
B34: Parking, Tolls & Rideshare | C34: 30 | D34: 30 | E34: =D34-C34 | F34: =IF(C13>0,C34/C13,0) | G34: =C34*12
B35: Clothing & Apparel | C35: 100 | D35: 100 | E35: =D35-C35 | F35: =IF(C13>0,C35/C13,0) | G35: =C35*12
B36: Entertainment & Recreation | C36: 100 | D36: 100 | E36: =D36-C36 | F36: =IF(C13>0,C36/C13,0) | G36: =C36*12
B37: Travel & Vacation | C37: 200 | D37: 200 | E37: =D37-C37 | F37: =IF(C13>0,C37/C13,0) | G37: =C37*12
B38: Personal Care & Beauty | C38: 80 | D38: 80 | E38: =D38-C38 | F38: =IF(C13>0,C38/C13,0) | G38: =C38*12
B39: Medical, Dental & Pharmacy | C39: 50 | D39: 50 | E39: =D39-C39 | F39: =IF(C13>0,C39/C13,0) | G39: =C39*12
B40: Home Maintenance & Repairs | C40: 100 | D40: 100 | E40: =D40-C40 | F40: =IF(C13>0,C40/C13,0) | G40: =C40*12
B41: Gifts & Charitable Donations | C41: 75 | D41: 75 | E41: =D41-C41 | F41: =IF(C13>0,C41/C13,0) | G41: =C41*12
B42: Pet Expenses | C42: 0 | D42: 0 | E42: =D42-C42 | F42: =IF(C13>0,C42/C13,0) | G42: =C42*12
B43: Childcare & Education | C43: 0 | D43: 0 | E43: =D43-C43 | F43: =IF(C13>0,C43/C13,0) | G43: =C43*12
B44: Miscellaneous / Catch-All | C44: 100 | D44: 100 | E44: =D44-C44 | F44: =IF(C13>0,C44/C13,0) | G44: =C44*12
B45: TOTAL VARIABLE EXPENSES | C45: =SUM(C31:C44) | D45: =SUM(D31:D44) | E45: =D45-C45 | F45: =IF(C13>0,C45/C13,0) | G45: =C45*12
B47: SAVINGS & INVESTMENTS
B48: 401(k) / 403(b) Contribution | C48: 1000 | D48: 1000 | E48: =D48-C48 | F48: =IF(C13>0,C48/C13,0) | G48: =C48*12
B49: Roth IRA Contribution | C49: 500 | D49: 500 | E49: =D49-C49 | F49: =IF(C13>0,C49/C13,0) | G49: =C49*12
B50: HSA Contribution | C50: 300 | D50: 300 | E50: =D50-C50 | F50: =IF(C13>0,C50/C13,0) | G50: =C50*12
B51: Taxable Brokerage Investment | C51: 500 | D51: 500 | E51: =D51-C51 | F51: =IF(C13>0,C51/C13,0) | G51: =C51*12
B52: Emergency Fund Top-Up | C52: 200 | D52: 200 | E52: =D52-C52 | F52: =IF(C13>0,C52/C13,0) | G52: =C52*12
B53: House / Goal Savings Fund | C53: 0 | D53: 0 | E53: =D53-C53 | F53: =IF(C13>0,C53/C13,0) | G53: =C53*12
B54: Other Savings / Sinking Funds | C54: 0 | D54: 0 | E54: =D54-C54 | F54: =IF(C13>0,C54/C13,0) | G54: =C54*12
B55: TOTAL SAVINGS & INVESTMENTS | C55: =SUM(C48:C54) | D55: =SUM(D48:D54) | E55: =D55-C55 | F55: =IF(C13>0,C55/C13,0) | G55: =C55*12
B57: SAVINGS RATE SUMMARY
B58: Total Monthly Income | C58: =C13 | F58: =C58*12 | G58: =C58*12
B59: Total Monthly Expenses | C59: =C28+C45 | F59: =C59*12 | G59: =C59*12
B60: Total Monthly Savings | C60: =C55 | F60: =C60*12 | G60: =C60*12
B61: Surplus / Unallocated | C61: =C13-C28-C45-C55 | F61: =C61*12 | G61: =C61*12
B62: SAVINGS RATE | C62: =IF(C13>0,C55/C13,0) | F62: =IF(C62>0,C62*100,0) | G62: =IF(C62>=0.5,"🔥 Excellent!",IF(C62>=0.3,"✅ On Track",IF(C62>=0.2,"⚠️ Improve","❌ Critical")))
B63: FIRE Projected Savings Rate Target | C63: 50.0% | F63: =IF(C63>0,C63*100,0) | G63: =IF(C63>=0.5,"🔥 Excellent!",IF(C63>=0.3,"✅ On Track",IF(C63>=0.2,"⚠️ Improve","❌ Critical")))

Sheet Investment Growth
B2: INVESTMENT GROWTH PROJECTIONS
B3: "Compound interest is the eighth wonder of the world. He who understands it, earns it." — Einstein
B5: INPUT PARAMETERS (yellow = edit me) | F5: FIRE TARGETS
B6: Current Age | C6: 32 | D6: ← edit | F6: Lean FIRE (20× expenses) | G6: =C13*20
B7: Annual Return Rate (nominal) | C7: 0.08 | D7: ← edit | F7: Standard FIRE (25× expenses) | G7: =C13*25
B8: Inflation Rate | C8: 0.03 | D8: ← edit | F8: Fat FIRE (33× expenses) | G8: =C13*33
B9: Real Return Rate (nom - inflation) | C9: =C7-C8 | D9: ← auto-calculated | F9: Barista FIRE (15× expenses) | G9: =C13*15
B10: Starting Portfolio Value ($) | C10: 50000 | D10: ← edit | F10: Annual Expenses (from Budget) | G10: =C13
B11: Monthly Contribution ($) | C11: 2000 | D11: ← edit | F11: Monthly Income Needed (FIRE) | G11: =C14*0.04/12
B12: Target Retirement Age | C12: 50 | D12: ← edit | F12: Projected Value at Retirement | G12: =IFERROR(INDEX(G19:G68,MATCH(C12,C19:C68,0)),0)
B13: Annual Retirement Expenses ($) | C13: ='Budget & Savings'!C28*12+'Budget & Savings'!C45*12 | D13: ← auto-calculated | F13: FI Progress % Today | G13: =IFERROR('Net Worth'!C42/C14,0)
B14: FIRE Number (25× annual expenses) | C14: =C13*25 | D14: ← auto-calculated | F14: Savings Rate (from Budget) | G14: ='Budget & Savings'!C62
B15: Years to FIRE | C15: =C12-C6 | D15: ← auto-calculated | F15: Monthly Contributions × 12 | G15: =C11*12
B17: YEAR-BY-YEAR COMPOUND GROWTH PROJECTION (50 Years)
B18: Year | C18: Age | D18: Opening Balance | E18: Annual Contributions | F18: Investment Return | G18: Closing Balance | H18: FIRE Target | I18: FI %
B19: 1 | C19: =C6+1 | D19: =C10 | E19: =C11*12 | F19: =(D19+E19/2)*C7 | G19: =D19+E19+F19 | H19: =C14 | I19: =IF(H19>0,G19/H19,0)
B20: 2 | C20: =C6+2 | D20: =G19 | E20: =C11*12 | F20: =(D20+E20/2)*C7 | G20: =D20+E20+F20 | H20: =C14 | I20: =IF(H20>0,G20/H20,0)
B21: 3 | C21: =C6+3 | D21: =G20 | E21: =C11*12 | F21: =(D21+E21/2)*C7 | G21: =D21+E21+F21 | H21: =C14 | I21: =IF(H21>0,G21/H21,0)
B22: 4 | C22: =C6+4 | D22: =G21 | E22: =C11*12 | F22: =(D22+E22/2)*C7 | G22: =D22+E22+F22 | H22: =C14 | I22: =IF(H22>0,G22/H22,0)
B23: 5 | C23: =C6+5 | D23: =G22 | E23: =C11*12 | F23: =(D23+E23/2)*C7 | G23: =D23+E23+F23 | H23: =C14 | I23: =IF(H23>0,G23/H23,0)
B24: 6 | C24: =C6+6 | D24: =G23 | E24: =C11*12 | F24: =(D24+E24/2)*C7 | G24: =D24+E24+F24 | H24: =C14 | I24: =IF(H24>0,G24/H24,0)
B25: 7 | C25: =C6+7 | D25: =G24 | E25: =C11*12 | F25: =(D25+E25/2)*C7 | G25: =D25+E25+F25 | H25: =C14 | I25: =IF(H25>0,G25/H25,0)
B26: 8 | C26: =C6+8 | D26: =G25 | E26: =C11*12 | F26: =(D26+E26/2)*C7 | G26: =D26+E26+F26 | H26: =C14 | I26: =IF(H26>0,G26/H26,0)
B27: 9 | C27: =C6+9 | D27: =G26 | E27: =C11*12 | F27: =(D27+E27/2)*C7 | G27: =D27+E27+F27 | H27: =C14 | I27: =IF(H27>0,G27/H27,0)
B28: 10 | C28: =C6+10 | D28: =G27 | E28: =C11*12 | F28: =(D28+E28/2)*C7 | G28: =D28+E28+F28 | H28: =C14 | I28: =IF(H28>0,G28/H28,0)
B29: 11 | C29: =C6+11 | D29: =G28 | E29: =C11*12 | F29: =(D29+E29/2)*C7 | G29: =D29+E29+F29 | H29: =C14 | I29: =IF(H29>0,G29/H29,0)
B30: 12 | C30: =C6+12 | D30: =G29 | E30: =C11*12 | F30: =(D30+E30/2)*C7 | G30: =D30+E30+F30 | H30: =C14 | I30: =IF(H30>0,G30/H30,0)
B31: 13 | C31: =C6+13 | D31: =G30 | E31: =C11*12 | F31: =(D31+E31/2)*C7 | G31: =D31+E31+F31 | H31: =C14 | I31: =IF(H31>0,G31/H31,0)
B32: 14 | C32: =C6+14 | D32: =G31 | E32: =C11*12 | F32: =(D32+E32/2)*C7 | G32: =D32+E32+F32 | H32: =C14 | I32: =IF(H32>0,G32/H32,0)
B33: 15 | C33: =C6+15 | D33: =G32 | E33: =C11*12 | F33: =(D33+E33/2)*C7 | G33: =D33+E33+F33 | H33: =C14 | I33: =IF(H33>0,G33/H33,0)
B34: 16 | C34: =C6+16 | D34: =G33 | E34: =C11*12 | F34: =(D34+E34/2)*C7 | G34: =D34+E34+F34 | H34: =C14 | I34: =IF(H34>0,G34/H34,0)
B35: 17 | C35: =C6+17 | D35: =G34 | E35: =C11*12 | F35: =(D35+E35/2)*C7 | G35: =D35+E35+F35 | H35: =C14 | I35: =IF(H35>0,G35/H35,0)
B36: 18 | C36: =C6+18 | D36: =G35 | E36: =C11*12 | F36: =(D36+E36/2)*C7 | G36: =D36+E36+F36 | H36: =C14 | I36: =IF(H36>0,G36/H36,0)
B37: 19 | C37: =C6+19 | D37: =G36 | E37: =C11*12 | F37: =(D37+E37/2)*C7 | G37: =D37+E37+F37 | H37: =C14 | I37: =IF(H37>0,G37/H37,0)
B38: 20 | C38: =C6+20 | D38: =G37 | E38: =C11*12 | F38: =(D38+E38/2)*C7 | G38: =D38+E38+F38 | H38: =C14 | I38: =IF(H38>0,G38/H38,0)
B39: 21 | C39: =C6+21 | D39: =G38 | E39: =C11*12 | F39: =(D39+E39/2)*C7 | G39: =D39+E39+F39 | H39: =C14 | I39: =IF(H39>0,G39/H39,0)
B40: 22 | C40: =C6+22 | D40: =G39 | E40: =C11*12 | F40: =(D40+E40/2)*C7 | G40: =D40+E40+F40 | H40: =C14 | I40: =IF(H40>0,G40/H40,0)
B41: 23 | C41: =C6+23 | D41: =G40 | E41: =C11*12 | F41: =(D41+E41/2)*C7 | G41: =D41+E41+F41 | H41: =C14 | I41: =IF(H41>0,G41/H41,0)
B42: 24 | C42: =C6+24 | D42: =G41 | E42: =C11*12 | F42: =(D42+E42/2)*C7 | G42: =D42+E42+F42 | H42: =C14 | I42: =IF(H42>0,G42/H42,0)
B43: 25 | C43: =C6+25 | D43: =G42 | E43: =C11*12 | F43: =(D43+E43/2)*C7 | G43: =D43+E43+F43 | H43: =C14 | I43: =IF(H43>0,G43/H43,0)
B44: 26 | C44: =C6+26 | D44: =G43 | E44: =C11*12 | F44: =(D44+E44/2)*C7 | G44: =D44+E44+F44 | H44: =C14 | I44: =IF(H44>0,G44/H44,0)
B45: 27 | C45: =C6+27 | D45: =G44 | E45: =C11*12 | F45: =(D45+E45/2)*C7 | G45: =D45+E45+F45 | H45: =C14 | I45: =IF(H45>0,G45/H45,0)
B46: 28 | C46: =C6+28 | D46: =G45 | E46: =C11*12 | F46: =(D46+E46/2)*C7 | G46: =D46+E46+F46 | H46: =C14 | I46: =IF(H46>0,G46/H46,0)
B47: 29 | C47: =C6+29 | D47: =G46 | E47: =C11*12 | F47: =(D47+E47/2)*C7 | G47: =D47+E47+F47 | H47: =C14 | I47: =IF(H47>0,G47/H47,0)
B48: 30 | C48: =C6+30 | D48: =G47 | E48: =C11*12 | F48: =(D48+E48/2)*C7 | G48: =D48+E48+F48 | H48: =C14 | I48: =IF(H48>0,G48/H48,0)
B49: 31 | C49: =C6+31 | D49: =G48 | E49: =C11*12 | F49: =(D49+E49/2)*C7 | G49: =D49+E49+F49 | H49: =C14 | I49: =IF(H49>0,G49/H49,0)
B50: 32 | C50: =C6+32 | D50: =G49 | E50: =C11*12 | F50: =(D50+E50/2)*C7 | G50: =D50+E50+F50 | H50: =C14 | I50: =IF(H50>0,G50/H50,0)
B51: 33 | C51: =C6+33 | D51: =G50 | E51: =C11*12 | F51: =(D51+E51/2)*C7 | G51: =D51+E51+F51 | H51: =C14 | I51: =IF(H51>0,G51/H51,0)
B52: 34 | C52: =C6+34 | D52: =G51 | E52: =C11*12 | F52: =(D52+E52/2)*C7 | G52: =D52+E52+F52 | H52: =C14 | I52: =IF(H52>0,G52/H52,0)
B53: 35 | C53: =C6+35 | D53: =G52 | E53: =C11*12 | F53: =(D53+E53/2)*C7 | G53: =D53+E53+F53 | H53: =C14 | I53: =IF(H53>0,G53/H53,0)
B54: 36 | C54: =C6+36 | D54: =G53 | E54: =C11*12 | F54: =(D54+E54/2)*C7 | G54: =D54+E54+F54 | H54: =C14 | I54: =IF(H54>0,G54/H54,0)
B55: 37 | C55: =C6+37 | D55: =G54 | E55: =C11*12 | F55: =(D55+E55/2)*C7 | G55: =D55+E55+F55 | H55: =C14 | I55: =IF(H55>0,G55/H55,0)
B56: 38 | C56: =C6+38 | D56: =G55 | E56: =C11*12 | F56: =(D56+E56/2)*C7 | G56: =D56+E56+F56 | H56: =C14 | I56: =IF(H56>0,G56/H56,0)
B57: 39 | C57: =C6+39 | D57: =G56 | E57: =C11*12 | F57: =(D57+E57/2)*C7 | G57: =D57+E57+F57 | H57: =C14 | I57: =IF(H57>0,G57/H57,0)
B58: 40 | C58: =C6+40 | D58: =G57 | E58: =C11*12 | F58: =(D58+E58/2)*C7 | G58: =D58+E58+F58 | H58: =C14 | I58: =IF(H58>0,G58/H58,0)
B59: 41 | C59: =C6+41 | D59: =G58 | E59: =C11*12 | F59: =(D59+E59/2)*C7 | G59: =D59+E59+F59 | H59: =C14 | I59: =IF(H59>0,G59/H59,0)
B60: 42 | C60: =C6+42 | D60: =G59 | E60: =C11*12 | F60: =(D60+E60/2)*C7 | G60: =D60+E60+F60 | H60: =C14 | I60: =IF(H60>0,G60/H60,0)
B61: 43 | C61: =C6+43 | D61: =G60 | E61: =C11*12 | F61: =(D61+E61/2)*C7 | G61: =D61+E61+F61 | H61: =C14 | I61: =IF(H61>0,G61/H61,0)
B62: 44 | C62: =C6+44 | D62: =G61 | E62: =C11*12 | F62: =(D62+E62/2)*C7 | G62: =D62+E62+F62 | H62: =C14 | I62: =IF(H62>0,G62/H62,0)
B63: 45 | C63: =C6+45 | D63: =G62 | E63: =C11*12 | F63: =(D63+E63/2)*C7 | G63: =D63+E63+F63 | H63: =C14 | I63: =IF(H63>0,G63/H63,0)
B64: 46 | C64: =C6+46 | D64: =G63 | E64: =C11*12 | F64: =(D64+E64/2)*C7 | G64: =D64+E64+F64 | H64: =C14 | I64: =IF(H64>0,G64/H64,0)
B65: 47 | C65: =C6+47 | D65: =G64 | E65: =C11*12 | F65: =(D65+E65/2)*C7 | G65: =D65+E65+F65 | H65: =C14 | I65: =IF(H65>0,G65/H65,0)
B66: 48 | C66: =C6+48 | D66: =G65 | E66: =C11*12 | F66: =(D66+E66/2)*C7 | G66: =D66+E66+F66 | H66: =C14 | I66: =IF(H66>0,G66/H66,0)
B67: 49 | C67: =C6+49 | D67: =G66 | E67: =C11*12 | F67: =(D67+E67/2)*C7 | G67: =D67+E67+F67 | H67: =C14 | I67: =IF(H67>0,G67/H67,0)
B68: 50 | C68: =C6+50 | D68: =G67 | E68: =C11*12 | F68: =(D68+E68/2)*C7 | G68: =D68+E68+F68 | H68: =C14 | I68: =IF(H68>0,G68/H68,0)

Sheet SWR Calculator
B2: SAFE WITHDRAWAL RATE & POST-RETIREMENT PLANNER
B3: The 4% Rule: withdraw 4% of portfolio annually — historically survived 95%+ of 30-year retirements (Trinity Study)
B5: RETIREMENT INPUTS | E5: SWR SCENARIO COMPARISON
B6: Parameter | C6: Value | E6: SWR Rate | F6: Annual Withdrawal | G6: FIRE # Required
B7: Portfolio at Retirement ($) | C7: =IFERROR(INDEX('Investment Growth'!G19:G68,MATCH('Investment Growth'!C12,'Investment Growth'!C19:C68,0)),0) | E7: Ultra-Conservative 2.5% | F7: =C7*0.025 | G7: =C8/0.025
B8: Annual Expenses in Retirement ($) | C8: ='Budget & Savings'!C28*12+'Budget & Savings'!C45*12 | E8: Conservative 3% | F8: =C7*0.03 | G8: =C8/0.03
B9: Inflation Rate | C9: 0.03 | E9: Moderate 3.5% | F9: =C7*0.035 | G9: =C8/0.035
B10: Safe Withdrawal Rate (SWR) | C10: 0.04 | E10: Classic 4% Rule ★ | F10: =C7*0.04 | G10: =C8/0.04
B11: Expected Portfolio Return Post-FIRE | C11: 0.07 | E11: Aggressive 4.5% | F11: =C7*0.045 | G11: =C8/0.045
B12: Retirement Duration (years) | C12: 35 | E12: Very Aggressive 5% | F12: =C7*0.05 | G12: =C8/0.05
B13: Retirement Age | C13: ='Investment Growth'!C12 | E13: YOLO 6% | F13: =C7*0.06 | G13: =C8/0.06
B15: RETIREMENT VIABILITY ANALYSIS
B16: Your Annual Withdrawal (at chosen SWR) | C16: =C7*C10
B17: Monthly Retirement Income | C17: =C7*C10/12
B18: FIRE Number Needed (your expenses÷SWR) | C18: =C8/C10
B19: Portfolio Surplus / Deficit vs FIRE# | C19: =C7-C8/C10
B20: FIRE READY? | C20: =IF(C7>=C8/C10,"✅ YES — You Have Achieved FIRE!","⏳ Not Yet — Keep Going!")
B21: Years Portfolio Lasts (no returns) | C21: =C7/C8
B22: Breakeven Return Rate Needed | C22: =IFERROR(C10-C9,0)
B24: PORTFOLIO LONGEVITY SIMULATION — Year-by-Year Post-Retirement
B25: Year | C25: Age | D25: Start Balance ($) | E25: Withdrawal (infl-adj) ($) | F25: Return on Portfolio ($) | G25: End Balance ($) | H25: Status
B26: 1 | C26: =C13+1 | D26: =C7 | E26: =C8*(1+C9)^0 | F26: =MAX(D26-E26,0)*C11 | G26: =MAX(D26-E26+F26,0) | H26: =IF(D26<=0,"💀 Depleted",IF(G26<=0,"💀 Depleted",IF(G26<C8,"⚠️ Warning","✅ Healthy")))
B27: 2 | C27: =C13+2 | D27: =G26 | E27: =C8*(1+C9)^1 | F27: =MAX(D27-E27,0)*C11 | G27: =MAX(D27-E27+F27,0) | H27: =IF(D27<=0,"💀 Depleted",IF(G27<=0,"💀 Depleted",IF(G27<C8,"⚠️ Warning","✅ Healthy")))
B28: 3 | C28: =C13+3 | D28: =G27 | E28: =C8*(1+C9)^2 | F28: =MAX(D28-E28,0)*C11 | G28: =MAX(D28-E28+F28,0) | H28: =IF(D28<=0,"💀 Depleted",IF(G28<=0,"💀 Depleted",IF(G28<C8,"⚠️ Warning","✅ Healthy")))
B29: 4 | C29: =C13+4 | D29: =G28 | E29: =C8*(1+C9)^3 | F29: =MAX(D29-E29,0)*C11 | G29: =MAX(D29-E29+F29,0) | H29: =IF(D29<=0,"💀 Depleted",IF(G29<=0,"💀 Depleted",IF(G29<C8,"⚠️ Warning","✅ Healthy")))
B30: 5 | C30: =C13+5 | D30: =G29 | E30: =C8*(1+C9)^4 | F30: =MAX(D30-E30,0)*C11 | G30: =MAX(D30-E30+F30,0) | H30: =IF(D30<=0,"💀 Depleted",IF(G30<=0,"💀 Depleted",IF(G30<C8,"⚠️ Warning","✅ Healthy")))
B31: 6 | C31: =C13+6 | D31: =G30 | E31: =C8*(1+C9)^5 | F31: =MAX(D31-E31,0)*C11 | G31: =MAX(D31-E31+F31,0) | H31: =IF(D31<=0,"💀 Depleted",IF(G31<=0,"💀 Depleted",IF(G31<C8,"⚠️ Warning","✅ Healthy")))
B32: 7 | C32: =C13+7 | D32: =G31 | E32: =C8*(1+C9)^6 | F32: =MAX(D32-E32,0)*C11 | G32: =MAX(D32-E32+F32,0) | H32: =IF(D32<=0,"💀 Depleted",IF(G32<=0,"💀 Depleted",IF(G32<C8,"⚠️ Warning","✅ Healthy")))
B33: 8 | C33: =C13+8 | D33: =G32 | E33: =C8*(1+C9)^7 | F33: =MAX(D33-E33,0)*C11 | G33: =MAX(D33-E33+F33,0) | H33: =IF(D33<=0,"💀 Depleted",IF(G33<=0,"💀 Depleted",IF(G33<C8,"⚠️ Warning","✅ Healthy")))
B34: 9 | C34: =C13+9 | D34: =G33 | E34: =C8*(1+C9)^8 | F34: =MAX(D34-E34,0)*C11 | G34: =MAX(D34-E34+F34,0) | H34: =IF(D34<=0,"💀 Depleted",IF(G34<=0,"💀 Depleted",IF(G34<C8,"⚠️ Warning","✅ Healthy")))
B35: 10 | C35: =C13+10 | D35: =G34 | E35: =C8*(1+C9)^9 | F35: =MAX(D35-E35,0)*C11 | G35: =MAX(D35-E35+F35,0) | H35: =IF(D35<=0,"💀 Depleted",IF(G35<=0,"💀 Depleted",IF(G35<C8,"⚠️ Warning","✅ Healthy")))
B36: 11 | C36: =C13+11 | D36: =G35 | E36: =C8*(1+C9)^10 | F36: =MAX(D36-E36,0)*C11 | G36: =MAX(D36-E36+F36,0) | H36: =IF(D36<=0,"💀 Depleted",IF(G36<=0,"💀 Depleted",IF(G36<C8,"⚠️ Warning","✅ Healthy")))
B37: 12 | C37: =C13+12 | D37: =G36 | E37: =C8*(1+C9)^11 | F37: =MAX(D37-E37,0)*C11 | G37: =MAX(D37-E37+F37,0) | H37: =IF(D37<=0,"💀 Depleted",IF(G37<=0,"💀 Depleted",IF(G37<C8,"⚠️ Warning","✅ Healthy")))
B38: 13 | C38: =C13+13 | D38: =G37 | E38: =C8*(1+C9)^12 | F38: =MAX(D38-E38,0)*C11 | G38: =MAX(D38-E38+F38,0) | H38: =IF(D38<=0,"💀 Depleted",IF(G38<=0,"💀 Depleted",IF(G38<C8,"⚠️ Warning","✅ Healthy")))
B39: 14 | C39: =C13+14 | D39: =G38 | E39: =C8*(1+C9)^13 | F39: =MAX(D39-E39,0)*C11 | G39: =MAX(D39-E39+F39,0) | H39: =IF(D39<=0,"💀 Depleted",IF(G39<=0,"💀 Depleted",IF(G39<C8,"⚠️ Warning","✅ Healthy")))
B40: 15 | C40: =C13+15 | D40: =G39 | E40: =C8*(1+C9)^14 | F40: =MAX(D40-E40,0)*C11 | G40: =MAX(D40-E40+F40,0) | H40: =IF(D40<=0,"💀 Depleted",IF(G40<=0,"💀 Depleted",IF(G40<C8,"⚠️ Warning","✅ Healthy")))
B41: 16 | C41: =C13+16 | D41: =G40 | E41: =C8*(1+C9)^15 | F41: =MAX(D41-E41,0)*C11 | G41: =MAX(D41-E41+F41,0) | H41: =IF(D41<=0,"💀 Depleted",IF(G41<=0,"💀 Depleted",IF(G41<C8,"⚠️ Warning","✅ Healthy")))
B42: 17 | C42: =C13+17 | D42: =G41 | E42: =C8*(1+C9)^16 | F42: =MAX(D42-E42,0)*C11 | G42: =MAX(D42-E42+F42,0) | H42: =IF(D42<=0,"💀 Depleted",IF(G42<=0,"💀 Depleted",IF(G42<C8,"⚠️ Warning","✅ Healthy")))
B43: 18 | C43: =C13+18 | D43: =G42 | E43: =C8*(1+C9)^17 | F43: =MAX(D43-E43,0)*C11 | G43: =MAX(D43-E43+F43,0) | H43: =IF(D43<=0,"💀 Depleted",IF(G43<=0,"💀 Depleted",IF(G43<C8,"⚠️ Warning","✅ Healthy")))
B44: 19 | C44: =C13+19 | D44: =G43 | E44: =C8*(1+C9)^18 | F44: =MAX(D44-E44,0)*C11 | G44: =MAX(D44-E44+F44,0) | H44: =IF(D44<=0,"💀 Depleted",IF(G44<=0,"💀 Depleted",IF(G44<C8,"⚠️ Warning","✅ Healthy")))
B45: 20 | C45: =C13+20 | D45: =G44 | E45: =C8*(1+C9)^19 | F45: =MAX(D45-E45,0)*C11 | G45: =MAX(D45-E45+F45,0) | H45: =IF(D45<=0,"💀 Depleted",IF(G45<=0,"💀 Depleted",IF(G45<C8,"⚠️ Warning","✅ Healthy")))
B46: 21 | C46: =C13+21 | D46: =G45 | E46: =C8*(1+C9)^20 | F46: =MAX(D46-E46,0)*C11 | G46: =MAX(D46-E46+F46,0) | H46: =IF(D46<=0,"💀 Depleted",IF(G46<=0,"💀 Depleted",IF(G46<C8,"⚠️ Warning","✅ Healthy")))
B47: 22 | C47: =C13+22 | D47: =G46 | E47: =C8*(1+C9)^21 | F47: =MAX(D47-E47,0)*C11 | G47: =MAX(D47-E47+F47,0) | H47: =IF(D47<=0,"💀 Depleted",IF(G47<=0,"💀 Depleted",IF(G47<C8,"⚠️ Warning","✅ Healthy")))
B48: 23 | C48: =C13+23 | D48: =G47 | E48: =C8*(1+C9)^22 | F48: =MAX(D48-E48,0)*C11 | G48: =MAX(D48-E48+F48,0) | H48: =IF(D48<=0,"💀 Depleted",IF(G48<=0,"💀 Depleted",IF(G48<C8,"⚠️ Warning","✅ Healthy")))
B49: 24 | C49: =C13+24 | D49: =G48 | E49: =C8*(1+C9)^23 | F49: =MAX(D49-E49,0)*C11 | G49: =MAX(D49-E49+F49,0) | H49: =IF(D49<=0,"💀 Depleted",IF(G49<=0,"💀 Depleted",IF(G49<C8,"⚠️ Warning","✅ Healthy")))
B50: 25 | C50: =C13+25 | D50: =G49 | E50: =C8*(1+C9)^24 | F50: =MAX(D50-E50,0)*C11 | G50: =MAX(D50-E50+F50,0) | H50: =IF(D50<=0,"💀 Depleted",IF(G50<=0,"💀 Depleted",IF(G50<C8,"⚠️ Warning","✅ Healthy")))
B51: 26 | C51: =C13+26 | D51: =G50 | E51: =C8*(1+C9)^25 | F51: =MAX(D51-E51,0)*C11 | G51: =MAX(D51-E51+F51,0) | H51: =IF(D51<=0,"💀 Depleted",IF(G51<=0,"💀 Depleted",IF(G51<C8,"⚠️ Warning","✅ Healthy")))
B52: 27 | C52: =C13+27 | D52: =G51 | E52: =C8*(1+C9)^26 | F52: =MAX(D52-E52,0)*C11 | G52: =MAX(D52-E52+F52,0) | H52: =IF(D52<=0,"💀 Depleted",IF(G52<=0,"💀 Depleted",IF(G52<C8,"⚠️ Warning","✅ Healthy")))
B53: 28 | C53: =C13+28 | D53: =G52 | E53: =C8*(1+C9)^27 | F53: =MAX(D53-E53,0)*C11 | G53: =MAX(D53-E53+F53,0) | H53: =IF(D53<=0,"💀 Depleted",IF(G53<=0,"💀 Depleted",IF(G53<C8,"⚠️ Warning","✅ Healthy")))
B54: 29 | C54: =C13+29 | D54: =G53 | E54: =C8*(1+C9)^28 | F54: =MAX(D54-E54,0)*C11 | G54: =MAX(D54-E54+F54,0) | H54: =IF(D54<=0,"💀 Depleted",IF(G54<=0,"💀 Depleted",IF(G54<C8,"⚠️ Warning","✅ Healthy")))
B55: 30 | C55: =C13+30 | D55: =G54 | E55: =C8*(1+C9)^29 | F55: =MAX(D55-E55,0)*C11 | G55: =MAX(D55-E55+F55,0) | H55: =IF(D55<=0,"💀 Depleted",IF(G55<=0,"💀 Depleted",IF(G55<C8,"⚠️ Warning","✅ Healthy")))
B56: 31 | C56: =C13+31 | D56: =G55 | E56: =C8*(1+C9)^30 | F56: =MAX(D56-E56,0)*C11 | G56: =MAX(D56-E56+F56,0) | H56: =IF(D56<=0,"💀 Depleted",IF(G56<=0,"💀 Depleted",IF(G56<C8,"⚠️ Warning","✅ Healthy")))
B57: 32 | C57: =C13+32 | D57: =G56 | E57: =C8*(1+C9)^31 | F57: =MAX(D57-E57,0)*C11 | G57: =MAX(D57-E57+F57,0) | H57: =IF(D57<=0,"💀 Depleted",IF(G57<=0,"💀 Depleted",IF(G57<C8,"⚠️ Warning","✅ Healthy")))
B58: 33 | C58: =C13+33 | D58: =G57 | E58: =C8*(1+C9)^32 | F58: =MAX(D58-E58,0)*C11 | G58: =MAX(D58-E58+F58,0) | H58: =IF(D58<=0,"💀 Depleted",IF(G58<=0,"💀 Depleted",IF(G58<C8,"⚠️ Warning","✅ Healthy")))
B59: 34 | C59: =C13+34 | D59: =G58 | E59: =C8*(1+C9)^33 | F59: =MAX(D59-E59,0)*C11 | G59: =MAX(D59-E59+F59,0) | H59: =IF(D59<=0,"💀 Depleted",IF(G59<=0,"💀 Depleted",IF(G59<C8,"⚠️ Warning","✅ Healthy")))
B60: 35 | C60: =C13+35 | D60: =G59 | E60: =C8*(1+C9)^34 | F60: =MAX(D60-E60,0)*C11 | G60: =MAX(D60-E60+F60,0) | H60: =IF(D60<=0,"💀 Depleted",IF(G60<=0,"💀 Depleted",IF(G60<C8,"⚠️ Warning","✅ Healthy")))
B61: 36 | C61: =C13+36 | D61: =G60 | E61: =C8*(1+C9)^35 | F61: =MAX(D61-E61,0)*C11 | G61: =MAX(D61-E61+F61,0) | H61: =IF(D61<=0,"💀 Depleted",IF(G61<=0,"💀 Depleted",IF(G61<C8,"⚠️ Warning","✅ Healthy")))
B62: 37 | C62: =C13+37 | D62: =G61 | E62: =C8*(1+C9)^36 | F62: =MAX(D62-E62,0)*C11 | G62: =MAX(D62-E62+F62,0) | H62: =IF(D62<=0,"💀 Depleted",IF(G62<=0,"💀 Depleted",IF(G62<C8,"⚠️ Warning","✅ Healthy")))
B63: 38 | C63: =C13+38 | D63: =G62 | E63: =C8*(1+C9)^37 | F63: =MAX(D63-E63,0)*C11 | G63: =MAX(D63-E63+F63,0) | H63: =IF(D63<=0,"💀 Depleted",IF(G63<=0,"💀 Depleted",IF(G63<C8,"⚠️ Warning","✅ Healthy")))
B64: 39 | C64: =C13+39 | D64: =G63 | E64: =C8*(1+C9)^38 | F64: =MAX(D64-E64,0)*C11 | G64: =MAX(D64-E64+F64,0) | H64: =IF(D64<=0,"💀 Depleted",IF(G64<=0,"💀 Depleted",IF(G64<C8,"⚠️ Warning","✅ Healthy")))
B65: 40 | C65: =C13+40 | D65: =G64 | E65: =C8*(1+C9)^39 | F65: =MAX(D65-E65,0)*C11 | G65: =MAX(D65-E65+F65,0) | H65: =IF(D65<=0,"💀 Depleted",IF(G65<=0,"💀 Depleted",IF(G65<C8,"⚠️ Warning","✅ Healthy")))
B66: 41 | C66: =C13+41 | D66: =G65 | E66: =C8*(1+C9)^40 | F66: =MAX(D66-E66,0)*C11 | G66: =MAX(D66-E66+F66,0) | H66: =IF(D66<=0,"💀 Depleted",IF(G66<=0,"💀 Depleted",IF(G66<C8,"⚠️ Warning","✅ Healthy")))
B67: 42 | C67: =C13+42 | D67: =G66 | E67: =C8*(1+C9)^41 | F67: =MAX(D67-E67,0)*C11 | G67: =MAX(D67-E67+F67,0) | H67: =IF(D67<=0,"💀 Depleted",IF(G67<=0,"💀 Depleted",IF(G67<C8,"⚠️ Warning","✅ Healthy")))
B68: 43 | C68: =C13+43 | D68: =G67 | E68: =C8*(1+C9)^42 | F68: =MAX(D68-E68,0)*C11 | G68: =MAX(D68-E68+F68,0) | H68: =IF(D68<=0,"💀 Depleted",IF(G68<=0,"💀 Depleted",IF(G68<C8,"⚠️ Warning","✅ Healthy")))
B69: 44 | C69: =C13+44 | D69: =G68 | E69: =C8*(1+C9)^43 | F69: =MAX(D69-E69,0)*C11 | G69: =MAX(D69-E69+F69,0) | H69: =IF(D69<=0,"💀 Depleted",IF(G69<=0,"💀 Depleted",IF(G69<C8,"⚠️ Warning","✅ Healthy")))
B70: 45 | C70: =C13+45 | D70: =G69 | E70: =C8*(1+C9)^44 | F70: =MAX(D70-E70,0)*C11 | G70: =MAX(D70-E70+F70,0) | H70: =IF(D70<=0,"💀 Depleted",IF(G70<=0,"💀 Depleted",IF(G70<C8,"⚠️ Warning","✅ Healthy")))
B71: 46 | C71: =C13+46 | D71: =G70 | E71: =C8*(1+C9)^45 | F71: =MAX(D71-E71,0)*C11 | G71: =MAX(D71-E71+F71,0) | H71: =IF(D71<=0,"💀 Depleted",IF(G71<=0,"💀 Depleted",IF(G71<C8,"⚠️ Warning","✅ Healthy")))
B72: 47 | C72: =C13+47 | D72: =G71 | E72: =C8*(1+C9)^46 | F72: =MAX(D72-E72,0)*C11 | G72: =MAX(D72-E72+F72,0) | H72: =IF(D72<=0,"💀 Depleted",IF(G72<=0,"💀 Depleted",IF(G72<C8,"⚠️ Warning","✅ Healthy")))
B73: 48 | C73: =C13+48 | D73: =G72 | E73: =C8*(1+C9)^47 | F73: =MAX(D73-E73,0)*C11 | G73: =MAX(D73-E73+F73,0) | H73: =IF(D73<=0,"💀 Depleted",IF(G73<=0,"💀 Depleted",IF(G73<C8,"⚠️ Warning","✅ Healthy")))
B74: 49 | C74: =C13+49 | D74: =G73 | E74: =C8*(1+C9)^48 | F74: =MAX(D74-E74,0)*C11 | G74: =MAX(D74-E74+F74,0) | H74: =IF(D74<=0,"💀 Depleted",IF(G74<=0,"💀 Depleted",IF(G74<C8,"⚠️ Warning","✅ Healthy")))
B75: 50 | C75: =C13+50 | D75: =G74 | E75: =C8*(1+C9)^49 | F75: =MAX(D75-E75,0)*C11 | G75: =MAX(D75-E75+F75,0) | H75: =IF(D75<=0,"💀 Depleted",IF(G75<=0,"💀 Depleted",IF(G75<C8,"⚠️ Warning","✅ Healthy")))
